paulistrings
