Metadata-Version: 2.1
Name: paulistrings
Version: 0.1.1
Summary: Quantum many body simulations with Pauli strings
Home-page: https://github.com/nicolasloizeau/PauliStrings.py
Author: Nicolas Loizeau
Author-email: Nicolas Loizeau <nicolasloizeau@gmail.com>
Maintainer-email: Nicolas Loizeau <nicolasloizeau@gmail.com>
License: MIT
Project-URL: bugs, https://github.com/nicolasloizeau/paulistrings/issues
Project-URL: changelog, https://github.com/nicolasloizeau/paulistrings/blob/master/changelog.md
Project-URL: homepage, https://github.com/nicolasloizeau/paulistrings
Requires-Python: >=3.10
License-File: LICENSE
Requires-Dist: typer
Provides-Extra: test
Requires-Dist: coverage; extra == "test"
Requires-Dist: pytest; extra == "test"
Requires-Dist: ruff; extra == "test"
Requires-Dist: ty; extra == "test"
Requires-Dist: ipdb; extra == "test"
